# Chapter 06 类文件结构

### 6.3.1 魔数与Class文件的版本

**魔数** : 确定文件格式, 防止文件扩展名被修改
- class文件魔数 : 0xCAFEBABE

版本号: 分为主版本号和次版本号
- 向下兼容, 不向上兼容

### 6.3.2 常量池

常量池:
- 字面量
- 符号引用
    - 包名
    - 全限定类名
    - 字段名和描述符
    - 方法名和描述符
    - 方法句柄和方法类型
    - 动态调用点和动态常量


### 示例

TestByteCode.java
```java
public class TestByteCode {

    private static final TestByteCode INSTANCE = new TestByteCode();
    private final String str = "Hello world";
    private int val = 1;

    private TestByteCode() {}

    public synchronized void fun() {

        int a = 1;
        int b = a + 3;

        Object lock = new Object();

        synchronized (lock) {

            for (int i = 0; i < 10; i++) {
                b += a;
            }
            int y = 1;
        }

        String y = "dfdsasdfas";
        int x[] = {1};

        runSomething(() -> x[0]++);
    }

    private static void runSomething(Runnable runnable) {
        runnable.run();
    }
}
```

TestByteCode.class
```
Classfile /E:/RaybanLeeeee/projects/test/test-jdk/target/classes/com/raybanleeeee/test/jvm/TestByteCode.class
  Last modified 2021年4月27日; size 1727 bytes
  MD5 checksum 5195321f0db7df00ddecec6a7d138c40
  Compiled from "TestByteCode.java"
public class com.raybanleeeee.test.jvm.TestByteCode
  minor version: 0
  major version: 52
  flags: (0x0021) ACC_PUBLIC, ACC_SUPER
  this_class: #10                         // com/raybanleeeee/test/jvm/TestByteCode
  super_class: #5                         // java/lang/Object
  interfaces: 0, fields: 3, methods: 5, attributes: 3
Constant pool:
   #1 = Methodref          #5.#48         // java/lang/Object."<init>":()V
   #2 = String             #49            // Hello world
   #3 = Fieldref           #10.#50        // com/raybanleeeee/test/jvm/TestByteCode.str:Ljava/lang/String;
   #4 = Fieldref           #10.#51        // com/raybanleeeee/test/jvm/TestByteCode.val:I
   #5 = Class              #52            // java/lang/Object
   #6 = String             #53            // dfdsasdfas
   #7 = InvokeDynamic      #0:#58         // #0:run:([I)Ljava/lang/Runnable;
   #8 = Methodref          #10.#59        // com/raybanleeeee/test/jvm/TestByteCode.runSomething:(Ljava/lang/Runnable;)V
   #9 = InterfaceMethodref #60.#61        // java/lang/Runnable.run:()V
  #10 = Class              #62            // com/raybanleeeee/test/jvm/TestByteCode
  #11 = Methodref          #10.#48        // com/raybanleeeee/test/jvm/TestByteCode."<init>":()V
  #12 = Fieldref           #10.#63        // com/raybanleeeee/test/jvm/TestByteCode.INSTANCE:Lcom/raybanleeeee/test/jvm/TestByteCode;
  #13 = Utf8               INSTANCE
  #14 = Utf8               Lcom/raybanleeeee/test/jvm/TestByteCode;
  #15 = Utf8               str
  #16 = Utf8               Ljava/lang/String;
  #17 = Utf8               ConstantValue
  #18 = Utf8               val
  #19 = Utf8               I
  #20 = Utf8               <init>
  #21 = Utf8               ()V
  #22 = Utf8               Code
  #23 = Utf8               LineNumberTable
  #24 = Utf8               LocalVariableTable
  #25 = Utf8               this
  #26 = Utf8               fun
  #27 = Utf8               i
  #28 = Utf8               a
  #29 = Utf8               b
  #30 = Utf8               lock
  #31 = Utf8               Ljava/lang/Object;
  #32 = Utf8               y
  #33 = Utf8               x
  #34 = Utf8               [I
  #35 = Utf8               StackMapTable
  #36 = Class              #62            // com/raybanleeeee/test/jvm/TestByteCode
  #37 = Class              #52            // java/lang/Object
  #38 = Class              #64            // java/lang/Throwable
  #39 = Utf8               runSomething
  #40 = Utf8               (Ljava/lang/Runnable;)V
  #41 = Utf8               runnable
  #42 = Utf8               Ljava/lang/Runnable;
  #43 = Utf8               lambda$fun$0
  #44 = Utf8               ([I)V
  #45 = Utf8               <clinit>
  #46 = Utf8               SourceFile
  #47 = Utf8               TestByteCode.java
  #48 = NameAndType        #20:#21        // "<init>":()V
  #49 = Utf8               Hello world
  #50 = NameAndType        #15:#16        // str:Ljava/lang/String;
  #51 = NameAndType        #18:#19        // val:I
  #52 = Utf8               java/lang/Object
  #53 = Utf8               dfdsasdfas
  #54 = Utf8               BootstrapMethods
  #55 = MethodHandle       6:#65          // REF_invokeStatic java/lang/invoke/LambdaMetafactory.metafactory:(Ljava/lang/invoke/MethodHandles$Lookup;Ljava/lang/String;Ljava/lang/invoke/MethodType;Lja
va/lang/invoke/MethodType;Ljava/lang/invoke/MethodHandle;Ljava/lang/invoke/MethodType;)Ljava/lang/invoke/CallSite;
  #56 = MethodType         #21            //  ()V
  #57 = MethodHandle       6:#66          // REF_invokeStatic com/raybanleeeee/test/jvm/TestByteCode.lambda$fun$0:([I)V
  #58 = NameAndType        #67:#68        // run:([I)Ljava/lang/Runnable;
  #59 = NameAndType        #39:#40        // runSomething:(Ljava/lang/Runnable;)V
  #60 = Class              #69            // java/lang/Runnable
  #61 = NameAndType        #67:#21        // run:()V
  #62 = Utf8               com/raybanleeeee/test/jvm/TestByteCode
  #63 = NameAndType        #13:#14        // INSTANCE:Lcom/raybanleeeee/test/jvm/TestByteCode;
  #64 = Utf8               java/lang/Throwable
  #65 = Methodref          #70.#71        // java/lang/invoke/LambdaMetafactory.metafactory:(Ljava/lang/invoke/MethodHandles$Lookup;Ljava/lang/String;Ljava/lang/invoke/MethodType;Ljava/lang/invoke/Me
thodType;Ljava/lang/invoke/MethodHandle;Ljava/lang/invoke/MethodType;)Ljava/lang/invoke/CallSite;
  #66 = Methodref          #10.#72        // com/raybanleeeee/test/jvm/TestByteCode.lambda$fun$0:([I)V
  #67 = Utf8               run
  #68 = Utf8               ([I)Ljava/lang/Runnable;
  #69 = Utf8               java/lang/Runnable
  #70 = Class              #73            // java/lang/invoke/LambdaMetafactory
  #71 = NameAndType        #74:#78        // metafactory:(Ljava/lang/invoke/MethodHandles$Lookup;Ljava/lang/String;Ljava/lang/invoke/MethodType;Ljava/lang/invoke/MethodType;Ljava/lang/invoke/MethodHa
ndle;Ljava/lang/invoke/MethodType;)Ljava/lang/invoke/CallSite;
  #72 = NameAndType        #43:#44        // lambda$fun$0:([I)V
  #73 = Utf8               java/lang/invoke/LambdaMetafactory
  #74 = Utf8               metafactory
  #75 = Class              #80            // java/lang/invoke/MethodHandles$Lookup
  #76 = Utf8               Lookup
  #77 = Utf8               InnerClasses
  #78 = Utf8               (Ljava/lang/invoke/MethodHandles$Lookup;Ljava/lang/String;Ljava/lang/invoke/MethodType;Ljava/lang/invoke/MethodType;Ljava/lang/invoke/MethodHandle;Ljava/lang/invoke/MethodT
ype;)Ljava/lang/invoke/CallSite;
  #79 = Class              #81            // java/lang/invoke/MethodHandles
  #80 = Utf8               java/lang/invoke/MethodHandles$Lookup
  #81 = Utf8               java/lang/invoke/MethodHandles
{
  public synchronized void fun();
    descriptor: ()V
    flags: (0x0021) ACC_PUBLIC, ACC_SYNCHRONIZED
    Code:
      stack=4, locals=7, args_size=1
         0: iconst_1
         1: istore_1
         2: iload_1
         3: iconst_3
         4: iadd
         5: istore_2
         6: new           #5                  // class java/lang/Object
         9: dup
        10: invokespecial #1                  // Method java/lang/Object."<init>":()V
        13: astore_3
        14: aload_3
        15: dup
        16: astore        4
        18: monitorenter
        19: iconst_0
        20: istore        5
        22: iload         5
        24: bipush        10
        26: if_icmpge     39
        29: iload_2
        30: iload_1
        31: iadd
        32: istore_2
        33: iinc          5, 1
        36: goto          22
        39: iconst_1
        40: istore        5
        42: aload         4
        44: monitorexit
        45: goto          56
        48: astore        6
        50: aload         4
        52: monitorexit
        53: aload         6
        55: athrow
        56: ldc           #6                  // String dfdsasdfas
        58: astore        4
        60: iconst_1
        61: newarray       int
        63: dup
        64: iconst_0
        65: iconst_1
        66: iastore
        67: astore        5
        69: aload         5
        71: invokedynamic #7,  0              // InvokeDynamic #0:run:([I)Ljava/lang/Runnable;
        76: invokestatic  #8                  // Method runSomething:(Ljava/lang/Runnable;)V
        79: return
      Exception table:
         from    to  target type
            19    45    48   any
            48    53    48   any
      LineNumberTable:
        line 13: 0
        line 14: 2
        line 16: 6
        line 18: 14
        line 20: 19
        line 21: 29
        line 20: 33
        line 23: 39
        line 24: 42
        line 26: 56
        line 27: 60
        line 29: 69
        line 30: 79
      LocalVariableTable:
        Start  Length  Slot  Name   Signature
           22      17     5     i   I
            0      80     0  this   Lcom/raybanleeeee/test/jvm/TestByteCode;
            2      78     1     a   I
            6      74     2     b   I
           14      66     3  lock   Ljava/lang/Object;
           60      20     4     y   Ljava/lang/String;
           69      11     5     x   [I
      StackMapTable: number_of_entries = 4
        frame_type = 255 /* full_frame */
          offset_delta = 22
          locals = [ class com/raybanleeeee/test/jvm/TestByteCode, int, int, class java/lang/Object, class java/lang/Object, int ]
          stack = []
        frame_type = 250 /* chop */
          offset_delta = 16
        frame_type = 72 /* same_locals_1_stack_item */
          stack = [ class java/lang/Throwable ]
        frame_type = 250 /* chop */
          offset_delta = 7

  static {};
    descriptor: ()V
    flags: (0x0008) ACC_STATIC
    Code:
      stack=2, locals=0, args_size=0
         0: new           #10                 // class com/raybanleeeee/test/jvm/TestByteCode
         3: dup
         4: invokespecial #11                 // Method "<init>":()V
         7: putstatic     #12                 // Field INSTANCE:Lcom/raybanleeeee/test/jvm/TestByteCode;
        10: return
      LineNumberTable:
        line 5: 0
}
SourceFile: "TestByteCode.java"
InnerClasses:
  public static final #76= #75 of #79;    // Lookup=class java/lang/invoke/MethodHandles$Lookup of class java/lang/invoke/MethodHandles
BootstrapMethods:
  0: #55 REF_invokeStatic java/lang/invoke/LambdaMetafactory.metafactory:(Ljava/lang/invoke/MethodHandles$Lookup;Ljava/lang/String;Ljava/lang/invoke/MethodType;Ljava/lang/invoke/MethodType;Ljava/lang
/invoke/MethodHandle;Ljava/lang/invoke/MethodType;)Ljava/lang/invoke/CallSite;
    Method arguments:
      #56 ()V
      #57 REF_invokeStatic com/raybanleeeee/test/jvm/TestByteCode.lambda$fun$0:([I)V
      #56 ()V
```